odoo/addons/stock_push_delay/README.rst
odoo/addons/stock_push_delay/__init__.py
odoo/addons/stock_push_delay/__manifest__.py
odoo/addons/stock_push_delay/i18n/stock_push_delay.pot
odoo/addons/stock_push_delay/models/__init__.py
odoo/addons/stock_push_delay/models/stock.py
odoo/addons/stock_push_delay/readme/CONTRIBUTORS.rst
odoo/addons/stock_push_delay/readme/DESCRIPTION.rst
odoo/addons/stock_push_delay/readme/USAGE.rst
odoo/addons/stock_push_delay/static/description/icon.png
odoo/addons/stock_push_delay/static/description/index.html
odoo11_addon_stock_push_delay-11.0.1.0.1.dist-info/METADATA
odoo11_addon_stock_push_delay-11.0.1.0.1.dist-info/WHEEL
odoo11_addon_stock_push_delay-11.0.1.0.1.dist-info/top_level.txt
odoo11_addon_stock_push_delay-11.0.1.0.1.dist-info/RECORD
